{
  "$schema": "https://raw.githubusercontent.com/earendil-works/pi/main/packages/coding-agent/src/modes/interactive/theme/theme-schema.json",
  "name": "pi-neon-oxide",
  "vars": {
    "bg": "#090a0f",
    "panel": "#10131c",
    "panelRaised": "#151927",
    "selected": "#202641",
    "text": "#e6e9f2",
    "muted": "#a5acc0",
    "dim": "#686f85",
    "border": "#2b3450",
    "borderMuted": "#1d2438",
    "accent": "#80ffea",
    "accentBright": "#b1fff3",
    "blue": "#8be9fd",
    "cyan": "#80ffea",
    "green": "#50fa7b",
    "yellow": "#f1fa8c",
    "orange": "#ffb86c",
    "red": "#ff6e6e",
    "pink": "#ff79c6",
    "purple": "#bd93f9"
  },
  "colors": {
    "accent": "accent",
    "border": "border",
    "borderAccent": "accentBright",
    "borderMuted": "borderMuted",
    "success": "green",
    "error": "red",
    "warning": "yellow",
    "muted": "muted",
    "dim": "dim",
    "text": "text",
    "thinkingText": "muted",

    "selectedBg": "selected",
    "userMessageBg": "panelRaised",
    "userMessageText": "text",
    "customMessageBg": "#211734",
    "customMessageText": "text",
    "customMessageLabel": "pink",
    "toolPendingBg": "panel",
    "toolSuccessBg": "#102719",
    "toolErrorBg": "#301a22",
    "toolTitle": "accentBright",
    "toolOutput": "text",

    "mdHeading": "pink",
    "mdLink": "accentBright",
    "mdLinkUrl": "dim",
    "mdCode": "yellow",
    "mdCodeBlock": "text",
    "mdCodeBlockBorder": "border",
    "mdQuote": "muted",
    "mdQuoteBorder": "borderMuted",
    "mdHr": "borderMuted",
    "mdListBullet": "accent",

    "toolDiffAdded": "green",
    "toolDiffRemoved": "red",
    "toolDiffContext": "muted",

    "syntaxComment": "dim",
    "syntaxKeyword": "pink",
    "syntaxFunction": "cyan",
    "syntaxVariable": "text",
    "syntaxString": "green",
    "syntaxNumber": "orange",
    "syntaxType": "blue",
    "syntaxOperator": "purple",
    "syntaxPunctuation": "muted",

    "thinkingOff": "borderMuted",
    "thinkingMinimal": "dim",
    "thinkingLow": "blue",
    "thinkingMedium": "cyan",
    "thinkingHigh": "pink",
    "thinkingXhigh": "red",

    "bashMode": "accentBright"
  },
  "export": {
    "pageBg": "bg",
    "cardBg": "panel",
    "infoBg": "#1d1a28"
  }
}
